tplearn/__init__.py
tplearn/regression.py
tplearn/tropalg.py
tplearn-0.1.0.dist-info/LICENSE
tplearn-0.1.0.dist-info/METADATA
tplearn-0.1.0.dist-info/WHEEL
tplearn-0.1.0.dist-info/top_level.txt
tplearn-0.1.0.dist-info/RECORD
